README.md
setup.py
vdomr/__init__.py
vdomr/component.py
vdomr/helpers.py
vdomr/vdom.py
vdomr/vdomr.py
vdomr/vdomrserver.py
vdomr.egg-info/PKG-INFO
vdomr.egg-info/SOURCES.txt
vdomr.egg-info/dependency_links.txt
vdomr.egg-info/requires.txt
vdomr.egg-info/top_level.txt
vdomr/components/__init__.py
vdomr/components/components.py
vdomr/devel/__init__.py
vdomr/devel/devel.py