Metadata-Version: 1.1
Name: vdomr
Version: 0.2.3
Summary: Interactive DOM components for python and jupyter
Home-page: https://github.com/magland/vdomr
Author: Jeremy Magland
Author-email: jmagland@flatironinstitute.org
License: UNKNOWN
Platform: UNKNOWN
Classifier: Programming Language :: Python :: 3
Classifier: License :: OSI Approved :: Apache Software License
Classifier: Operating System :: OS Independent
